{
    "coord": {
        "lon": -73.5878,
        "lat": 45.5088
    },
    "weather": [
        {
            "id": 804,
            "main": "Clouds",
            "description": "overcast clouds",
            "icon": "04d"
        }
    ],
    "base": "stations",
    "main": {
        "temp": 8.48,
        "feels_like": 5.08,
        "temp_min": 8.01,
        "temp_max": 8.67,
        "pressure": 1009,
        "humidity": 85,
        "sea_level": 1009,
        "grnd_level": 1005
    },
    "visibility": 10000,
    "wind": {
        "speed": 6.69,
        "deg": 60
    },
    "clouds": {
        "all": 100
    },
    "dt": 1748003126,
    "sys": {
        "type": 1,
        "id": 498,
        "country": "CA",
        "sunrise": 1747991731,
        "sunset": 1748046422
    },
    "timezone": -14400,
    "id": 6077243,
    "name": "Montreal",
    "cod": 200
}