{
    "coord": {
        "lon": -73.5878,
        "lat": 45.5088
    },
    "weather": [
        {
            "id": 801,
            "main": "Clouds",
            "description": "few clouds",
            "icon": "02n"
        }
    ],
    "base": "stations",
    "main": {
        "temp": 16.38,
        "feels_like": 15.56,
        "temp_min": 16.38,
        "temp_max": 16.38,
        "pressure": 1021,
        "humidity": 57,
        "sea_level": 1021,
        "grnd_level": 1017
    },
    "visibility": 10000,
    "wind": {
        "speed": 2.34,
        "deg": 244,
        "gust": 8.34
    },
    "clouds": {
        "all": 22
    },
    "dt": 1759538754,
    "sys": {
        "country": "CA",
        "sunrise": 1759488912,
        "sunset": 1759530671
    },
    "timezone": -14400,
    "id": 6077243,
    "name": "Montreal",
    "cod": 200
}