{
    "coord": {
        "lon": -73.5878,
        "lat": 45.5088
    },
    "weather": [
        {
            "id": 803,
            "main": "Clouds",
            "description": "broken clouds",
            "icon": "04n"
        }
    ],
    "base": "stations",
    "main": {
        "temp": 24.04,
        "feels_like": 23.86,
        "temp_min": 22.56,
        "temp_max": 24.67,
        "pressure": 1015,
        "humidity": 52,
        "sea_level": 1015,
        "grnd_level": 1012
    },
    "visibility": 10000,
    "wind": {
        "speed": 4.63,
        "deg": 320
    },
    "clouds": {
        "all": 75
    },
    "dt": 1753923240,
    "sys": {
        "type": 1,
        "id": 498,
        "country": "CA",
        "sunrise": 1753868166,
        "sunset": 1753921516
    },
    "timezone": -14400,
    "id": 6077243,
    "name": "Montreal",
    "cod": 200
}