{
    "coord": {
        "lon": -73.5878,
        "lat": 45.5088
    },
    "weather": [
        {
            "id": 600,
            "main": "Snow",
            "description": "light snow",
            "icon": "13n"
        }
    ],
    "base": "stations",
    "main": {
        "temp": -10.97,
        "feels_like": -17.97,
        "temp_min": -11.65,
        "temp_max": -9.86,
        "pressure": 1018,
        "humidity": 87,
        "sea_level": 1018,
        "grnd_level": 1014
    },
    "visibility": 6437,
    "wind": {
        "speed": 6.69,
        "deg": 50,
        "gust": 10.29
    },
    "snow": {
        "1h": 0.12
    },
    "clouds": {
        "all": 100
    },
    "dt": 1739687880,
    "sys": {
        "type": 1,
        "id": 498,
        "country": "CA",
        "sunrise": 1739706866,
        "sunset": 1739744560
    },
    "timezone": -18000,
    "id": 6077243,
    "name": "Montreal",
    "cod": 200
}