{
    "coord": {
        "lon": -73.5878,
        "lat": 45.5088
    },
    "weather": [
        {
            "id": 803,
            "main": "Clouds",
            "description": "broken clouds",
            "icon": "04n"
        }
    ],
    "base": "stations",
    "main": {
        "temp": -5.38,
        "feels_like": -12.07,
        "temp_min": -6.63,
        "temp_max": -4.76,
        "pressure": 1012,
        "humidity": 78,
        "sea_level": 1012,
        "grnd_level": 1009
    },
    "visibility": 10000,
    "wind": {
        "speed": 5.66,
        "deg": 260
    },
    "clouds": {
        "all": 75
    },
    "dt": 1769129565,
    "sys": {
        "type": 1,
        "id": 498,
        "country": "CA",
        "sunrise": 1769084737,
        "sunset": 1769118355
    },
    "timezone": -18000,
    "id": 6077243,
    "name": "Montreal",
    "cod": 200
}