{
    "coord": {
        "lon": -73.5878,
        "lat": 45.5088
    },
    "weather": [
        {
            "id": 803,
            "main": "Clouds",
            "description": "broken clouds",
            "icon": "04n"
        }
    ],
    "base": "stations",
    "main": {
        "temp": 16.35,
        "feels_like": 15.42,
        "temp_min": 15.08,
        "temp_max": 17.52,
        "pressure": 1015,
        "humidity": 53,
        "sea_level": 1015,
        "grnd_level": 1012
    },
    "visibility": 10000,
    "wind": {
        "speed": 4.12,
        "deg": 350
    },
    "clouds": {
        "all": 75
    },
    "dt": 1780020389,
    "sys": {
        "type": 1,
        "id": 498,
        "country": "CA",
        "sunrise": 1779959506,
        "sunset": 1780014711
    },
    "timezone": -14400,
    "id": 6077243,
    "name": "Montreal",
    "cod": 200
}